libsense/__init__.py
libsense/constant.py
libsense/function.py
libsense/analyze/__init__.py
libsense/feed/__init__.py
libsense/feed/camera.py
libsense/feed/file.py
libsense/feed/parameter.py
libsense/feed/speaker.py
libsense/feed/audio/__init__.py
libsense/feed/audio/function.py
libsense/feed/audio/parameter.py
libsense/feed/audio/prompt.py
libsense/feed/core/__init__.py
libsense/feed/core/rwlock.py
libsense/feed/core/struct.py
libsense/feed/mock/__init__.py
libsense/feed/video/__init__.py
libsense/feed/video/function.py
libsense/feed/video/parameter.py
libsense/feed/video/prompt.py
libsense/ingest/__init__.py
serve/__init__.py
libsense-0.0.0.dist-info/LICENSE
libsense-0.0.0.dist-info/METADATA
libsense-0.0.0.dist-info/WHEEL
libsense-0.0.0.dist-info/top_level.txt
libsense-0.0.0.dist-info/RECORD
