Metadata-Version: 2.1
Name: libsense
Version: 0.0.0
Summary: Libsense library
Home-page: UNKNOWN
Author: System Design Studio
Author-email: silveryfu@gmail.com
License: Apache License, Version 2.0
Platform: UNKNOWN
Requires-Python: >=3.10
License-File: LICENSE
Requires-Dist: openai
Requires-Dist: pyyaml
Requires-Dist: numpy
Requires-Dist: flask
Requires-Dist: pyaudio
Requires-Dist: opencv-python-headless
Requires-Dist: SpeechRecognition
Requires-Dist: pocketsphinx
Requires-Dist: jiwer
Requires-Dist: moviepy
Requires-Dist: libem
